MANIFEST.in
pyproject.toml
setup.py
./requirements/requirements.txt
./requirements/test_requirements.txt
RG_model.egg-info/PKG-INFO
RG_model.egg-info/SOURCES.txt
RG_model.egg-info/dependency_links.txt
RG_model.egg-info/requires.txt
RG_model.egg-info/top_level.txt
regression_model/VERSION
regression_model/__init__.py
regression_model/pipeline.py
regression_model/predict.py
regression_model/train_pipeline.py
regression_model/config_base/__init__.py
regression_model/config_base/core_test.py
regression_model/processing/__init__.py
regression_model/processing/data_manager.py
regression_model/trained_models/__init__.py
regression_model/trained_models/regression_model_output_v0.0.1.pkl